nonebot_plugin_searchgames/__init__.py
nonebot_plugin_searchgames/templates/CSS/steam.css
nonebot_plugin_searchgames/templates/font/Mengshen-Handwritten.ttf
nonebot_plugin_searchgames/templates/font/荆南麦圆体-Regular.ttf
nonebot_plugin_searchgames/templates/steam免费游戏.html
nonebot_plugin_searchgames/templates/steam游戏查询.html
nonebot_plugin_searchgames/templates/switch游戏查询.html
nonebot_plugin_searchgames-0.1.4.dist-info/LICENSE
nonebot_plugin_searchgames-0.1.4.dist-info/METADATA
nonebot_plugin_searchgames-0.1.4.dist-info/WHEEL
nonebot_plugin_searchgames-0.1.4.dist-info/RECORD
