Metadata-Version: 2.1
Name: nonebot-plugin-searchgames
Version: 0.1.4
Summary: 简单查询游戏steam和switch平台游戏信息的小插件
Home-page: https://github.com/NYAGO666/nonebot-plugin-Searchgames
License: MIT
Author: NYAGO666
Requires-Python: >3.10
Classifier: License :: OSI Approved :: MIT License
Classifier: Programming Language :: Python :: 3
Classifier: Programming Language :: Python :: 3.11
Classifier: Programming Language :: Python :: 3.12
Classifier: Programming Language :: Python :: 3.13
Requires-Dist: httpx (>=0.27.0)
Requires-Dist: nonebot-adapter-onebot (>=2.4.0)
Requires-Dist: nonebot-plugin-htmlrender (>=0.3.0)
Requires-Dist: nonebot2 (>=2.3.0)
Requires-Dist: pydantic (>=2.8.0)
Requires-Dist: requests (>=2.31.0,<3.0.0)
Project-URL: Repository, https://github.com/NYAGO666/nonebot-plugin-Searchgames
